json_keystore/keystore.py
json_keystore-0.0.1.dist-info/LICENSE
json_keystore-0.0.1.dist-info/METADATA
json_keystore-0.0.1.dist-info/WHEEL
json_keystore-0.0.1.dist-info/top_level.txt
json_keystore-0.0.1.dist-info/RECORD
