Metadata-Version: 2.1
Name: json-keystore
Version: 0.0.1
Summary: Python Library for Encrypted JSON
Home-page: https://github.com/brianddk/json-keystore
Author: brianddk
Author-email: brianddk <brianddk@users.noreply.github.com>
Maintainer-email: brianddk <brianddk@users.noreply.github.com>
License: Apache-2.0
Project-URL: Homepage, https://github.com/brianddk/json-keystore
Project-URL: Repository, https://github.com/brianddk/json-keystore.git
Project-URL: Issues, https://github.com/brianddk/json-keystore/issues
Project-URL: Discussions, https://github.com/brianddk/json-keystore/discussions
Project-URL: Donations, https://tippin.me/@dkbriand
Keywords: json,encryption
Classifier: Development Status :: 3 - Alpha
Classifier: Intended Audience :: Developers
Classifier: Topic :: Software Development :: Libraries
Classifier: License :: OSI Approved :: Apache Software License
Classifier: Programming Language :: Python :: 3
Requires-Python: >=3.8.2
License-File: LICENSE
Requires-Dist: trezor >=0.13.8
Requires-Dist: pyjson5 >=1.6.6
Provides-Extra: dev
Requires-Dist: build >=1.1.1 ; extra == 'dev'
Requires-Dist: twine >=5.0.0 ; extra == 'dev'
Requires-Dist: black >=24.3.0 ; extra == 'dev'
Requires-Dist: flake8 >=7.0.0 ; extra == 'dev'
Requires-Dist: isort >=5.13.2 ; extra == 'dev'
